CHANGES.txt
README.txt
setup.py
Products/__init__.py
Products.ReflectoImageScales.egg-info/PKG-INFO
Products.ReflectoImageScales.egg-info/SOURCES.txt
Products.ReflectoImageScales.egg-info/dependency_links.txt
Products.ReflectoImageScales.egg-info/namespace_packages.txt
Products.ReflectoImageScales.egg-info/not-zip-safe
Products.ReflectoImageScales.egg-info/requires.txt
Products.ReflectoImageScales.egg-info/top_level.txt
Products/ReflectoImageScales/__init__.py
Products/ReflectoImageScales/browser.py
Products/ReflectoImageScales/configure.zcml
docs/LICENSE.GPL
docs/LICENSE.txt