Metadata-Version: 1.0
Name: Products.ReflectoImageScales
Version: 1.0
Summary: Thumbnails for Reflecto images
Home-page: http://pypi.python.org/pypi/Products.ReflectoImageScales
Author: Laurence Rowe
Author-email: laurence@lrowe.co.uk
License: GPL
Keywords: Plone
Platform: UNKNOWN
Classifier: Framework :: Plone
Classifier: Programming Language :: Python
